stairsval/__init__.py
stairsval/core/__init__.py
stairsval/core/aggregator.py
stairsval/core/database/Adapter.py
stairsval/core/database/DBWrapper.py
stairsval/core/database/DataSource.py
stairsval/core/database/__init__.py
stairsval/core/database/history.py
stairsval/core/database/local_schedule_loader.py
stairsval/core/database/localmschmadapter.py
stairsval/core/dataset_processors/BaseDataset.py
stairsval/core/dataset_processors/KSGDataset.py
stairsval/core/dataset_processors/ObjectNameProcessor.py
stairsval/core/dataset_processors/PlanDataset.py
stairsval/core/dataset_processors/S7KSG.py
stairsval/core/dataset_processors/ValidationDataset.py
stairsval/core/dataset_processors/__init__.py
stairsval/core/expert_metrics_estimator.py
stairsval/core/project_preprocessor.py
stairsval/core/stats_calculator.py
stairsval/factory/validator_factory.py
stairsval/validation_checks/AbstractChecker.py
stairsval/validation_checks/JournalChecker.py
stairsval/validation_checks/ResourcesChecker.py
stairsval/validation_checks/TimeChecker.py
stairsval/validation_checks/WorksChecker.py
stairsval/validation_checks/__init__.py
stairsval/validators/BaseValidator.py
stairsval/validators/GPNValidator.py
stairsval/validators/S7Validator.py
stairsval/validators/__init__.py
stairsval-0.4.2.dist-info/METADATA
stairsval-0.4.2.dist-info/WHEEL
stairsval-0.4.2.dist-info/RECORD
