Metadata-Version: 2.1
Name: stairsval
Version: 0.4.2
Summary: 
Author: jrzkaminski
Author-email: 86363785+jrzkaminski@users.noreply.github.com
Requires-Python: >=3.9,<3.11
Classifier: Programming Language :: Python :: 3
Classifier: Programming Language :: Python :: 3.9
Classifier: Programming Language :: Python :: 3.10
Requires-Dist: matplotlib (>=3.6.2)
Requires-Dist: numpy (>=1.25.0)
Requires-Dist: numpy-indexed (==0.3.5)
Requires-Dist: pandas (>=2.0.0)
Requires-Dist: reportlab
Requires-Dist: rich (>=13.5.3)
Requires-Dist: scipy (>=1.8.0)
Requires-Dist: seaborn (>=0.11.2)
Requires-Dist: stairs-mro (>=0.2.1)
